[{"model": "admin.logentry", "pk": 1, "fields": {"action_time": "2024-03-07T21:57:44.685Z", "user": 1, "content_type": 7, "object_id": "4", "object_repr": "Стал известен первый соперник Новака Джоковича на «Мастерсе» в Индиан-Уэллсе", "action_flag": 1, "change_message": "[{\"added\": {}}]"}}, {"model": "admin.logentry", "pk": 2, "fields": {"action_time": "2024-03-07T22:05:08.661Z", "user": 1, "content_type": 7, "object_id": "4", "object_repr": "Стал известен первый соперник Новака Джоковича на «Мастерсе» в Индиан-Уэллсе", "action_flag": 2, "change_message": "[{\"changed\": {\"fields\": [\"\\u0421\\u043e\\u0434\\u0435\\u0440\\u0436\\u0430\\u043d\\u0438\\u0435\"]}}]"}}, {"model": "admin.logentry", "pk": 3, "fields": {"action_time": "2024-03-11T18:55:27.035Z", "user": 1, "content_type": 8, "object_id": "1", "object_repr": "Category object (1)", "action_flag": 1, "change_message": "[{\"added\": {}}]"}}, {"model": "admin.logentry", "pk": 4, "fields": {"action_time": "2024-03-11T19:03:46.913Z", "user": 1, "content_type": 7, "object_id": "2", "object_repr": "В «Спартаке» назвали причину проблем с газоном на домашнем стадионе", "action_flag": 2, "change_message": "[{\"changed\": {\"fields\": [\"Category\"]}}]"}}, {"model": "admin.logentry", "pk": 5, "fields": {"action_time": "2024-03-11T19:20:34.375Z", "user": 1, "content_type": 8, "object_id": "2", "object_repr": "Хоккей", "action_flag": 1, "change_message": "[{\"added\": {}}]"}}, {"model": "admin.logentry", "pk": 6, "fields": {"action_time": "2024-03-11T19:20:43.208Z", "user": 1, "content_type": 8, "object_id": "3", "object_repr": "Теннис", "action_flag": 1, "change_message": "[{\"added\": {}}]"}}, {"model": "admin.logentry", "pk": 7, "fields": {"action_time": "2024-03-11T19:20:52.906Z", "user": 1, "content_type": 8, "object_id": "4", "object_repr": "Другое", "action_flag": 1, "change_message": "[{\"added\": {}}]"}}, {"model": "admin.logentry", "pk": 8, "fields": {"action_time": "2024-03-11T19:22:42.449Z", "user": 1, "content_type": 7, "object_id": "1", "object_repr": "Маскота «Интернасьонала» обвинили в сексуальных домогательствах — TyC Sports", "action_flag": 2, "change_message": "[{\"changed\": {\"fields\": [\"\\u041a\\u0430\\u0442\\u0435\\u0433\\u043e\\u0440\\u0438\\u044f\"]}}]"}}, {"model": "admin.logentry", "pk": 9, "fields": {"action_time": "2024-03-11T19:22:50.089Z", "user": 1, "content_type": 7, "object_id": "4", "object_repr": "Стал известен первый соперник Новака Джоковича на «Мастерсе» в Индиан-Уэллсе", "action_flag": 2, "change_message": "[{\"changed\": {\"fields\": [\"\\u041a\\u0430\\u0442\\u0435\\u0433\\u043e\\u0440\\u0438\\u044f\"]}}]"}}, {"model": "admin.logentry", "pk": 10, "fields": {"action_time": "2024-03-11T19:23:03.620Z", "user": 1, "content_type": 7, "object_id": "3", "object_repr": "В «Спартаке» заявили, что ситуация с Промесом непростая", "action_flag": 2, "change_message": "[{\"changed\": {\"fields\": [\"\\u041a\\u0430\\u0442\\u0435\\u0433\\u043e\\u0440\\u0438\\u044f\"]}}]"}}, {"model": "admin.logentry", "pk": 11, "fields": {"action_time": "2024-03-14T20:42:43.352Z", "user": 1, "content_type": 7, "object_id": "3", "object_repr": "В «Спартаке» заявили, что ситуация с Промесом непростая", "action_flag": 2, "change_message": "[{\"changed\": {\"fields\": [\"\\u0421\\u043e\\u0434\\u0435\\u0440\\u0436\\u0430\\u043d\\u0438\\u0435\"]}}]"}}, {"model": "admin.logentry", "pk": 12, "fields": {"action_time": "2024-03-18T18:31:50.677Z", "user": 1, "content_type": 7, "object_id": "4", "object_repr": "Стал известен первый соперник Новака Джоковича на «Мастерсе» в Индиан-Уэллсе", "action_flag": 2, "change_message": "[{\"changed\": {\"fields\": [\"\\u0418\\u0437\\u043e\\u0431\\u0440\\u0430\\u0436\\u0435\\u043d\\u0438\\u0435\"]}}]"}}, {"model": "admin.logentry", "pk": 13, "fields": {"action_time": "2024-03-18T18:32:01.125Z", "user": 1, "content_type": 7, "object_id": "4", "object_repr": "Стал известен первый соперник Новака Джоковича на «Мастерсе» в Индиан-Уэллсе", "action_flag": 2, "change_message": "[{\"changed\": {\"fields\": [\"\\u0418\\u0437\\u043e\\u0431\\u0440\\u0430\\u0436\\u0435\\u043d\\u0438\\u0435\"]}}]"}}, {"model": "admin.logentry", "pk": 14, "fields": {"action_time": "2024-03-19T12:08:14.286Z", "user": 1, "content_type": 7, "object_id": "5", "object_repr": "Агент Шипачёва и Войнова рассказал о дальнейшей судьбе хоккеистов «Ак Барса»", "action_flag": 1, "change_message": "[{\"added\": {}}]"}}, {"model": "admin.logentry", "pk": 15, "fields": {"action_time": "2024-03-19T12:10:09.939Z", "user": 1, "content_type": 7, "object_id": "6", "object_repr": "Кравец ответил на вопрос, что не получилось за время его пребывания в «Авангарде»", "action_flag": 1, "change_message": "[{\"added\": {}}]"}}, {"model": "admin.logentry", "pk": 16, "fields": {"action_time": "2024-03-19T12:44:05.783Z", "user": 1, "content_type": 7, "object_id": "6", "object_repr": "Кравец ответил на вопрос, что не получилось за время его пребывания в «Авангарде»", "action_flag": 2, "change_message": "[{\"changed\": {\"fields\": [\"\\u041e\\u043f\\u0443\\u0431\\u043b\\u0438\\u043a\\u043e\\u0432\\u0430\\u043d\\u043e\"]}}]"}}, {"model": "admin.logentry", "pk": 17, "fields": {"action_time": "2024-03-19T12:44:05.784Z", "user": 1, "content_type": 7, "object_id": "4", "object_repr": "Стал известен первый соперник Новака Джоковича на «Мастерсе» в Индиан-Уэллсе", "action_flag": 2, "change_message": "[{\"changed\": {\"fields\": [\"\\u041e\\u043f\\u0443\\u0431\\u043b\\u0438\\u043a\\u043e\\u0432\\u0430\\u043d\\u043e\"]}}]"}}, {"model": "admin.logentry", "pk": 18, "fields": {"action_time": "2024-03-19T12:44:05.785Z", "user": 1, "content_type": 7, "object_id": "3", "object_repr": "В «Спартаке» заявили, что ситуация с Промесом непростая", "action_flag": 2, "change_message": "[{\"changed\": {\"fields\": [\"\\u041e\\u043f\\u0443\\u0431\\u043b\\u0438\\u043a\\u043e\\u0432\\u0430\\u043d\\u043e\"]}}]"}}, {"model": "admin.logentry", "pk": 19, "fields": {"action_time": "2024-03-19T12:44:05.786Z", "user": 1, "content_type": 7, "object_id": "1", "object_repr": "Маскота «Интернасьонала» обвинили в сексуальных домогательствах — TyC Sports", "action_flag": 2, "change_message": "[{\"changed\": {\"fields\": [\"\\u041e\\u043f\\u0443\\u0431\\u043b\\u0438\\u043a\\u043e\\u0432\\u0430\\u043d\\u043e\"]}}]"}}, {"model": "admin.logentry", "pk": 20, "fields": {"action_time": "2024-03-19T12:44:05.787Z", "user": 1, "content_type": 7, "object_id": "2", "object_repr": "В «Спартаке» назвали причину проблем с газоном на домашнем стадионе", "action_flag": 2, "change_message": "[{\"changed\": {\"fields\": [\"\\u041e\\u043f\\u0443\\u0431\\u043b\\u0438\\u043a\\u043e\\u0432\\u0430\\u043d\\u043e\"]}}]"}}, {"model": "admin.logentry", "pk": 21, "fields": {"action_time": "2024-03-19T12:44:41.929Z", "user": 1, "content_type": 7, "object_id": "5", "object_repr": "Агент Шипачёва и Войнова рассказал о дальнейшей судьбе хоккеистов «Ак Барса»", "action_flag": 2, "change_message": "[{\"changed\": {\"fields\": [\"\\u041e\\u043f\\u0443\\u0431\\u043b\\u0438\\u043a\\u043e\\u0432\\u0430\\u043d\\u043e\"]}}]"}}, {"model": "admin.logentry", "pk": 22, "fields": {"action_time": "2024-03-19T12:45:26.519Z", "user": 1, "content_type": 7, "object_id": "3", "object_repr": "В «Спартаке» заявили, что ситуация с Промесом непростая", "action_flag": 2, "change_message": "[{\"changed\": {\"fields\": [\"\\u0418\\u0437\\u043e\\u0431\\u0440\\u0430\\u0436\\u0435\\u043d\\u0438\\u0435\"]}}]"}}, {"model": "admin.logentry", "pk": 23, "fields": {"action_time": "2024-03-22T10:27:18.738Z", "user": 1, "content_type": 7, "object_id": "7", "object_repr": "Матвей Сафонов покинул расположение сборной России", "action_flag": 1, "change_message": "[{\"added\": {}}]"}}, {"model": "admin.logentry", "pk": 24, "fields": {"action_time": "2024-03-22T10:28:18.988Z", "user": 1, "content_type": 7, "object_id": "8", "object_repr": "Сафиуллин обыграл Шварцмана на старте турнира в Майами", "action_flag": 1, "change_message": "[{\"added\": {}}]"}}, {"model": "admin.logentry", "pk": 25, "fields": {"action_time": "2024-03-22T10:29:14.833Z", "user": 1, "content_type": 7, "object_id": "9", "object_repr": "Сборная Архангельской области одержала победу в мужской эстафете на чемпионате России", "action_flag": 1, "change_message": "[{\"added\": {}}]"}}, {"model": "admin.logentry", "pk": 26, "fields": {"action_time": "2024-03-22T10:30:14.682Z", "user": 1, "content_type": 7, "object_id": "10", "object_repr": "Кучеров занял 4-е место в НХЛ по скорости достижения 120 очков среди крайних форвардов", "action_flag": 1, "change_message": "[{\"added\": {}}]"}}, {"model": "admin.logentry", "pk": 27, "fields": {"action_time": "2024-03-22T10:30:59.360Z", "user": 1, "content_type": 7, "object_id": "11", "object_repr": "Танасиевич: Бабич был в трансферных списках московского «Динамо»", "action_flag": 1, "change_message": "[{\"added\": {}}]"}}, {"model": "admin.logentry", "pk": 28, "fields": {"action_time": "2024-03-22T10:33:39.730Z", "user": 1, "content_type": 7, "object_id": "12", "object_repr": "Илья Ишков: из «Урала» можно уехать в Европу, вспомните пример Зинченко и «Уфы»", "action_flag": 1, "change_message": "[{\"added\": {}}]"}}, {"model": "admin.logentry", "pk": 29, "fields": {"action_time": "2024-03-28T09:37:06.618Z", "user": 1, "content_type": 7, "object_id": "13", "object_repr": "«Ожидал, что будет хуже». Медведев — о чилийских болельщиках в матче с Харри", "action_flag": 1, "change_message": "[{\"added\": {}}]"}}, {"model": "admin.logentry", "pk": 30, "fields": {"action_time": "2024-03-28T09:38:21.332Z", "user": 1, "content_type": 7, "object_id": "14", "object_repr": "«Бавария» может назначить экс-тренера «Спартака» после ухода Тухеля", "action_flag": 1, "change_message": "[{\"added\": {}}]"}}, {"model": "admin.logentry", "pk": 31, "fields": {"action_time": "2024-04-05T09:41:03.403Z", "user": 1, "content_type": 7, "object_id": "17", "object_repr": "Виктория Сливко одержала победу в марафоне на ЧР в Увате", "action_flag": 3, "change_message": ""}}, {"model": "admin.logentry", "pk": 32, "fields": {"action_time": "2024-04-05T09:41:03.472Z", "user": 1, "content_type": 7, "object_id": "16", "object_repr": "Виктория Сливко одержала победу в марафоне на ЧР в Увате", "action_flag": 3, "change_message": ""}}, {"model": "admin.logentry", "pk": 33, "fields": {"action_time": "2024-04-05T09:41:03.545Z", "user": 1, "content_type": 7, "object_id": "15", "object_repr": "Виктория Сливко одержала победу в марафоне на ЧР в Увате", "action_flag": 3, "change_message": ""}}, {"model": "admin.logentry", "pk": 34, "fields": {"action_time": "2024-04-05T09:41:13.230Z", "user": 1, "content_type": 7, "object_id": "18", "object_repr": "Виктория Сливко одержала победу в марафоне на ЧР в Увате", "action_flag": 2, "change_message": "[{\"changed\": {\"fields\": [\"\\u041e\\u043f\\u0443\\u0431\\u043b\\u0438\\u043a\\u043e\\u0432\\u0430\\u043d\\u043e\", \"\\u041a\\u0430\\u0442\\u0435\\u0433\\u043e\\u0440\\u0438\\u044f\"]}}]"}}, {"model": "admin.logentry", "pk": 35, "fields": {"action_time": "2024-04-05T09:48:34.823Z", "user": 1, "content_type": 7, "object_id": "19", "object_repr": "Карим Халили выиграл марафон на 40 км на чемпионате России в Увате", "action_flag": 2, "change_message": "[{\"changed\": {\"fields\": [\"\\u041e\\u043f\\u0443\\u0431\\u043b\\u0438\\u043a\\u043e\\u0432\\u0430\\u043d\\u043e\"]}}]"}}, {"model": "admin.logentry", "pk": 36, "fields": {"action_time": "2024-04-05T09:50:16.104Z", "user": 1, "content_type": 7, "object_id": "20", "object_repr": "Президент СБР Майгуров прокомментировал итоги чемпионата России по биатлону", "action_flag": 3, "change_message": ""}}, {"model": "admin.logentry", "pk": 37, "fields": {"action_time": "2024-04-05T09:50:34.721Z", "user": 1, "content_type": 7, "object_id": "21", "object_repr": "Президент СБР Майгуров прокомментировал итоги чемпионата России по биатлону", "action_flag": 3, "change_message": ""}}, {"model": "admin.logentry", "pk": 38, "fields": {"action_time": "2024-04-07T15:58:20.232Z", "user": 1, "content_type": 7, "object_id": "22", "object_repr": "Заварухин — после 2:3 от «Металлурга»: охота больше от нападающих", "action_flag": 2, "change_message": "[{\"changed\": {\"fields\": [\"\\u0418\\u0437\\u043e\\u0431\\u0440\\u0430\\u0436\\u0435\\u043d\\u0438\\u0435\", \"\\u041e\\u043f\\u0443\\u0431\\u043b\\u0438\\u043a\\u043e\\u0432\\u0430\\u043d\\u043e\"]}}]"}}, {"model": "admin.logentry", "pk": 39, "fields": {"action_time": "2024-04-09T20:13:03.633Z", "user": 1, "content_type": 7, "object_id": "32", "object_repr": "вфыв", "action_flag": 3, "change_message": ""}}, {"model": "admin.logentry", "pk": 40, "fields": {"action_time": "2024-04-09T20:13:03.712Z", "user": 1, "content_type": 7, "object_id": "31", "object_repr": "Стал известен соперник Медведева во втором круге «Мастерса» в Монте-Карло", "action_flag": 3, "change_message": ""}}, {"model": "admin.logentry", "pk": 41, "fields": {"action_time": "2024-04-09T20:13:03.774Z", "user": 1, "content_type": 7, "object_id": "30", "object_repr": "Наталья Терентьева впервые прокомментировала уход из группы Юрия Бородавко", "action_flag": 3, "change_message": ""}}, {"model": "admin.logentry", "pk": 42, "fields": {"action_time": "2024-04-09T20:13:03.845Z", "user": 1, "content_type": 7, "object_id": "29", "object_repr": "Даниил Медведев объяснил, почему очень ждёт «Ролан Гаррос»", "action_flag": 3, "change_message": ""}}, {"model": "admin.logentry", "pk": 43, "fields": {"action_time": "2024-04-09T20:13:03.929Z", "user": 1, "content_type": 7, "object_id": "28", "object_repr": "Ральф Рангник ответил на вопрос о переговорах с «Баварией»", "action_flag": 3, "change_message": ""}}, {"model": "admin.logentry", "pk": 44, "fields": {"action_time": "2024-04-12T14:45:20.221Z", "user": 1, "content_type": 7, "object_id": "33", "object_repr": "Йоханнес Клебо объявил о возвращении в сборную Норвегии", "action_flag": 3, "change_message": ""}}, {"model": "admin.logentry", "pk": 45, "fields": {"action_time": "2024-04-12T14:47:04.614Z", "user": 1, "content_type": 7, "object_id": "34", "object_repr": "Йоханнес Клебо объявил о возвращении в сборную Норвегии", "action_flag": 3, "change_message": ""}}, {"model": "admin.logentry", "pk": 46, "fields": {"action_time": "2024-04-12T14:59:06.754Z", "user": 1, "content_type": 7, "object_id": "36", "object_repr": "Йоханнес Клебо объявил о возвращении в сборную Норвегии", "action_flag": 3, "change_message": ""}}, {"model": "admin.logentry", "pk": 47, "fields": {"action_time": "2024-04-12T14:59:06.843Z", "user": 1, "content_type": 7, "object_id": "35", "object_repr": "Йоханнес Клебо объявил о возвращении в сборную Норвегии", "action_flag": 3, "change_message": ""}}, {"model": "admin.logentry", "pk": 48, "fields": {"action_time": "2024-04-12T15:08:12.018Z", "user": 1, "content_type": 7, "object_id": "37", "object_repr": "Йоханнес Клебо объявил о возвращении в сборную Норвегии", "action_flag": 3, "change_message": ""}}, {"model": "admin.logentry", "pk": 49, "fields": {"action_time": "2024-04-12T15:16:38.110Z", "user": 1, "content_type": 7, "object_id": "38", "object_repr": "Йоханнес Клебо объявил о возвращении в сборную Норвегии", "action_flag": 3, "change_message": ""}}, {"model": "admin.logentry", "pk": 50, "fields": {"action_time": "2024-04-12T15:24:56.689Z", "user": 1, "content_type": 7, "object_id": "27", "object_repr": "У «Манчестер Сити» есть договорённость с Лукасом Пакета об условиях контракта — Ауна", "action_flag": 3, "change_message": ""}}, {"model": "admin.logentry", "pk": 51, "fields": {"action_time": "2024-04-12T15:24:56.784Z", "user": 1, "content_type": 7, "object_id": "26", "object_repr": "У «Манчестер Сити» есть договорённость с Лукасом Пакета об условиях контракта — Ауна", "action_flag": 3, "change_message": ""}}, {"model": "admin.logentry", "pk": 52, "fields": {"action_time": "2024-04-12T15:24:56.861Z", "user": 1, "content_type": 7, "object_id": "25", "object_repr": "У «Манчестер Сити» есть договорённость с Лукасом Пакета об условиях контракта — Ауна", "action_flag": 3, "change_message": ""}}, {"model": "admin.logentry", "pk": 53, "fields": {"action_time": "2024-04-12T15:24:56.942Z", "user": 1, "content_type": 7, "object_id": "24", "object_repr": "У «Манчестер Сити» есть договорённость с Лукасом Пакета об условиях контракта — Ауна", "action_flag": 3, "change_message": ""}}, {"model": "admin.logentry", "pk": 54, "fields": {"action_time": "2024-04-12T15:24:57.021Z", "user": 1, "content_type": 7, "object_id": "23", "object_repr": "У «Манчестер Сити» есть договорённость с Лукасом Пакета об условиях контракта — Ауна", "action_flag": 3, "change_message": ""}}, {"model": "admin.logentry", "pk": 55, "fields": {"action_time": "2024-04-12T17:29:01.844Z", "user": 1, "content_type": 7, "object_id": "44", "object_repr": "Алексей Морозов рассказал о плюсах увеличения числа легионеров в КХЛ", "action_flag": 3, "change_message": ""}}, {"model": "admin.logentry", "pk": 56, "fields": {"action_time": "2024-04-12T17:29:01.936Z", "user": 1, "content_type": 7, "object_id": "43", "object_repr": "Алексей Морозов рассказал о плюсах увеличения числа легионеров в КХЛ", "action_flag": 3, "change_message": ""}}, {"model": "admin.logentry", "pk": 57, "fields": {"action_time": "2024-04-12T17:29:02.036Z", "user": 1, "content_type": 7, "object_id": "42", "object_repr": "Алексей Морозов рассказал о плюсах увеличения числа легионеров в КХЛ", "action_flag": 3, "change_message": ""}}, {"model": "admin.logentry", "pk": 58, "fields": {"action_time": "2024-04-12T17:29:02.113Z", "user": 1, "content_type": 7, "object_id": "41", "object_repr": "Алексей Морозов рассказал о плюсах увеличения числа легионеров в КХЛ", "action_flag": 3, "change_message": ""}}, {"model": "admin.logentry", "pk": 59, "fields": {"action_time": "2024-04-12T17:31:42.944Z", "user": 1, "content_type": 7, "object_id": "45", "object_repr": "Алексей Морозов рассказал о плюсах увеличения числа легионеров в КХЛ", "action_flag": 3, "change_message": ""}}, {"model": "admin.logentry", "pk": 60, "fields": {"action_time": "2024-04-15T19:22:10.951Z", "user": 1, "content_type": 7, "object_id": "48", "object_repr": "«Я тоже человек!» Руне обвинил судью в предвзятости по ходу матча с Синнером в Монте-Карло", "action_flag": 2, "change_message": "[{\"changed\": {\"fields\": [\"\\u041e\\u043f\\u0443\\u0431\\u043b\\u0438\\u043a\\u043e\\u0432\\u0430\\u043d\\u043e\"]}}]"}}, {"model": "admin.logentry", "pk": 61, "fields": {"action_time": "2024-04-15T19:22:40.400Z", "user": 1, "content_type": 7, "object_id": "48", "object_repr": "«Я тоже человек!» Руне обвинил судью в предвзятости по ходу матча с Синнером в Монте-Карло", "action_flag": 2, "change_message": "[{\"changed\": {\"fields\": [\"\\u041e\\u043f\\u0443\\u0431\\u043b\\u0438\\u043a\\u043e\\u0432\\u0430\\u043d\\u043e\"]}}]"}}, {"model": "admin.logentry", "pk": 62, "fields": {"action_time": "2024-04-19T12:06:41.259Z", "user": 1, "content_type": 7, "object_id": "51", "object_repr": "Овечкин заявил, что его улыбка стала вирусной и вновь улыбнулся для прессы в раздевалке", "action_flag": 3, "change_message": ""}}, {"model": "auth.permission", "pk": 1, "fields": {"name": "Can add log entry", "content_type": 1, "codename": "add_logentry"}}, {"model": "auth.permission", "pk": 2, "fields": {"name": "Can change log entry", "content_type": 1, "codename": "change_logentry"}}, {"model": "auth.permission", "pk": 3, "fields": {"name": "Can delete log entry", "content_type": 1, "codename": "delete_logentry"}}, {"model": "auth.permission", "pk": 4, "fields": {"name": "Can view log entry", "content_type": 1, "codename": "view_logentry"}}, {"model": "auth.permission", "pk": 5, "fields": {"name": "Can add permission", "content_type": 2, "codename": "add_permission"}}, {"model": "auth.permission", "pk": 6, "fields": {"name": "Can change permission", "content_type": 2, "codename": "change_permission"}}, {"model": "auth.permission", "pk": 7, "fields": {"name": "Can delete permission", "content_type": 2, "codename": "delete_permission"}}, {"model": "auth.permission", "pk": 8, "fields": {"name": "Can view permission", "content_type": 2, "codename": "view_permission"}}, {"model": "auth.permission", "pk": 9, "fields": {"name": "Can add group", "content_type": 3, "codename": "add_group"}}, {"model": "auth.permission", "pk": 10, "fields": {"name": "Can change group", "content_type": 3, "codename": "change_group"}}, {"model": "auth.permission", "pk": 11, "fields": {"name": "Can delete group", "content_type": 3, "codename": "delete_group"}}, {"model": "auth.permission", "pk": 12, "fields": {"name": "Can view group", "content_type": 3, "codename": "view_group"}}, {"model": "auth.permission", "pk": 13, "fields": {"name": "Can add user", "content_type": 4, "codename": "add_user"}}, {"model": "auth.permission", "pk": 14, "fields": {"name": "Can change user", "content_type": 4, "codename": "change_user"}}, {"model": "auth.permission", "pk": 15, "fields": {"name": "Can delete user", "content_type": 4, "codename": "delete_user"}}, {"model": "auth.permission", "pk": 16, "fields": {"name": "Can view user", "content_type": 4, "codename": "view_user"}}, {"model": "auth.permission", "pk": 17, "fields": {"name": "Can add content type", "content_type": 5, "codename": "add_contenttype"}}, {"model": "auth.permission", "pk": 18, "fields": {"name": "Can change content type", "content_type": 5, "codename": "change_contenttype"}}, {"model": "auth.permission", "pk": 19, "fields": {"name": "Can delete content type", "content_type": 5, "codename": "delete_contenttype"}}, {"model": "auth.permission", "pk": 20, "fields": {"name": "Can view content type", "content_type": 5, "codename": "view_contenttype"}}, {"model": "auth.permission", "pk": 21, "fields": {"name": "Can add session", "content_type": 6, "codename": "add_session"}}, {"model": "auth.permission", "pk": 22, "fields": {"name": "Can change session", "content_type": 6, "codename": "change_session"}}, {"model": "auth.permission", "pk": 23, "fields": {"name": "Can delete session", "content_type": 6, "codename": "delete_session"}}, {"model": "auth.permission", "pk": 24, "fields": {"name": "Can view session", "content_type": 6, "codename": "view_session"}}, {"model": "auth.permission", "pk": 25, "fields": {"name": "Can add article", "content_type": 7, "codename": "add_article"}}, {"model": "auth.permission", "pk": 26, "fields": {"name": "Can change article", "content_type": 7, "codename": "change_article"}}, {"model": "auth.permission", "pk": 27, "fields": {"name": "Can delete article", "content_type": 7, "codename": "delete_article"}}, {"model": "auth.permission", "pk": 28, "fields": {"name": "Can view article", "content_type": 7, "codename": "view_article"}}, {"model": "auth.permission", "pk": 29, "fields": {"name": "Can add category", "content_type": 8, "codename": "add_category"}}, {"model": "auth.permission", "pk": 30, "fields": {"name": "Can change category", "content_type": 8, "codename": "change_category"}}, {"model": "auth.permission", "pk": 31, "fields": {"name": "Can delete category", "content_type": 8, "codename": "delete_category"}}, {"model": "auth.permission", "pk": 32, "fields": {"name": "Can view category", "content_type": 8, "codename": "view_category"}}, {"model": "auth.user", "pk": 1, "fields": {"password": "pbkdf2_sha256$720000$D95DqdFLU3K8Yeh2ouWPnS$MftcDURlZXE6T17pcqP8nyMMzkMI73RNP5DOoZ8ykyU=", "last_login": "2024-04-19T13:08:02.968Z", "is_superuser": true, "username": "admin", "first_name": "", "last_name": "", "email": "", "is_staff": true, "is_active": true, "date_joined": "2024-03-07T18:51:17.240Z", "groups": [], "user_permissions": []}}, {"model": "contenttypes.contenttype", "pk": 1, "fields": {"app_label": "admin", "model": "logentry"}}, {"model": "contenttypes.contenttype", "pk": 2, "fields": {"app_label": "auth", "model": "permission"}}, {"model": "contenttypes.contenttype", "pk": 3, "fields": {"app_label": "auth", "model": "group"}}, {"model": "contenttypes.contenttype", "pk": 4, "fields": {"app_label": "auth", "model": "user"}}, {"model": "contenttypes.contenttype", "pk": 5, "fields": {"app_label": "contenttypes", "model": "contenttype"}}, {"model": "contenttypes.contenttype", "pk": 6, "fields": {"app_label": "sessions", "model": "session"}}, {"model": "contenttypes.contenttype", "pk": 7, "fields": {"app_label": "sport_news", "model": "article"}}, {"model": "contenttypes.contenttype", "pk": 8, "fields": {"app_label": "sport_news", "model": "category"}}, {"model": "sessions.session", "pk": "2mdjbshhupijgkn110e521m7nl8bi5ya", "fields": {"session_data": ".eJxVjEsOAiEQBe_C2hD5NIhL956BQHcjowaSYWZlvLtOMgvdvqp6LxHTutS4Dp7jROIslDj8bjnhg9sG6J7arUvsbZmnLDdF7nTIayd-Xnb376CmUb81W5vZKQ_KIJyC9i4zZfYlaAPgCY3PSgOrkgogYCBrSB9Rk7NWJyveH-CcN9Q:1rnc6N:o1yS6aGq2Wd2tOTc3GR2QI2BqigaWliQEEbI7OWlTwk", "expire_date": "2024-04-05T10:26:19.149Z"}}, {"model": "sessions.session", "pk": "3brkcnm0k7bin183b3x20ez1q9qt69ti", "fields": {"session_data": ".eJxVjEsOAiEQBe_C2hD5NIhL956BQHcjowaSYWZlvLtOMgvdvqp6LxHTutS4Dp7jROIslDj8bjnhg9sG6J7arUvsbZmnLDdF7nTIayd-Xnb376CmUb81W5vZKQ_KIJyC9i4zZfYlaAPgCY3PSgOrkgogYCBrSB9Rk7NWJyveH-CcN9Q:1rxnyF:5aXq5gHn_215timLrSW5n5bTrI3w-qz8BHuit5qfO5c", "expire_date": "2024-05-03T13:08:03.044Z"}}, {"model": "sessions.session", "pk": "jzggg4kmebb2d4fdk6v5ha182nbq19kg", "fields": {"session_data": ".eJxVjEsOAiEQBe_C2hD5NIhL956BQHcjowaSYWZlvLtOMgvdvqp6LxHTutS4Dp7jROIslDj8bjnhg9sG6J7arUvsbZmnLDdF7nTIayd-Xnb376CmUb81W5vZKQ_KIJyC9i4zZfYlaAPgCY3PSgOrkgogYCBrSB9Rk7NWJyveH-CcN9Q:1riIsX:NwpelFJgFz0u8yNKL596fmAr_NWZE0qFcFkBfTQgZZ0", "expire_date": "2024-03-21T18:54:05.911Z"}}, {"model": "sessions.session", "pk": "k2wf72g6twahepvmyxxwikh54j074kck", "fields": {"session_data": ".eJxVjEsOAiEQBe_C2hD5NIhL956BQHcjowaSYWZlvLtOMgvdvqp6LxHTutS4Dp7jROIslDj8bjnhg9sG6J7arUvsbZmnLDdF7nTIayd-Xnb376CmUb81W5vZKQ_KIJyC9i4zZfYlaAPgCY3PSgOrkgogYCBrSB9Rk7NWJyveH-CcN9Q:1rtUts:A5qRl7bGknfUFokboOrrc0niOGxNB3t8r9kS7ke3_o8", "expire_date": "2024-04-21T15:57:44.847Z"}}, {"model": "sport_news.article", "pk": 1, "fields": {"title": "Маскота «Интернасьонала» обвинили в сексуальных домогательствах — TyC Sports", "content": "По информации источника, Кумпель утверждает, что маскот постоянно ей жестикулировал, а после победного гола обнимал и лапал, схватил за голову и поцеловал. При этом бразильский клуб уже предоставил полиции записи с камер видеонаблюдения, а на время расследования отстранил сотрудника. Отметим, что победный мяч был забит на 90+8-й минуте игры Аланом Патриком, который реализовал пенальти.", "image": "", "create_date": "2024-02-27T18:23:16.671Z", "update_date": "2024-03-19T12:44:05.786Z", "is_published": true, "category": 1}}, {"model": "sport_news.article", "pk": 2, "fields": {"title": "В «Спартаке» назвали причину проблем с газоном на домашнем стадионе", "content": "«Зимой клуб проводил плановую реновацию футбольного поля. Реновация проходила в плановом режиме. В начале февраля поле находилось в идеальном состоянии.", "image": "", "create_date": "2024-02-29T18:34:06.106Z", "update_date": "2024-03-19T12:44:05.786Z", "is_published": true, "category": 1}}, {"model": "sport_news.article", "pk": 3, "fields": {"title": "В «Спартаке» заявили, что ситуация с Промесом непростая", "content": "<b>Сегодня</b>, 29 февраля, стало известно, что нападающий московского «Спартака» Квинси Промес не смог вылететь из ОАЭ в Санкт-Петербург, поскольку был задержан на пограничном контроле в аэропорту Дубая «Аль-Мактум».", "image": "uploads/2024/03/19/kak-kvinsi-promes-sidit-v-tyurme-v-oae_1710777430275015506.jpg", "create_date": "2024-02-29T18:37:39.307Z", "update_date": "2024-03-19T12:45:26.517Z", "is_published": true, "category": 1}}, {"model": "sport_news.article", "pk": 4, "fields": {"title": "Стал известен первый соперник Новака Джоковича на «Мастерсе» в Индиан-Уэллсе", "content": "Определился первый соперник 24-кратного чемпиона турниров «Большого шлема», первой ракетки мира сербского теннисиста Новака Джоковича на турнире серии «Мастерс» в Индиан-Уэллсе (США). Им стал 69-я ракетка мира из Австралии Александар Вукич.\r\nВ матче первого круга Вукич со счётом 7:6 (7:4), 7:6 (8:6) обыграл 149-ю ракетку мира из Японии Синтаро Мочизуки (Q). Встреча теннисистов продлилась 1 час и 55 минут.", "image": "uploads/2024/03/18/stal-izvesten-pervyj-sopernik-novaka-dzhokovicha-na-masterse-v-indian_21z7Kbd.jpg", "create_date": "2024-03-07T21:57:44.682Z", "update_date": "2024-03-19T12:44:05.784Z", "is_published": true, "category": 3}}, {"model": "sport_news.article", "pk": 5, "fields": {"title": "Агент Шипачёва и Войнова рассказал о дальнейшей судьбе хоккеистов «Ак Барса»", "content": "Хоккейный агент Станислав Романов, представляющий интересы защитника «Ак Барса» Вячеслава Войнова и нападающего казанского клуба Вадима Шипачёва, рассказал о дальнейшей судьбе хоккеистов казанского клуба.\r\n\r\n«У Вадима Шипачёва и Вячеслава Войнова действующие контракты с «Ак Барсом». Никаких переговоров об обмене в другие клубы или расторжении действующих соглашений мы не ведём», — сказал Романов в беседе с корреспондентом «Чемпионата» Павлом Панышевым.\r\n\r\nНапомним, у хоккеистов действующие контракты с «Ак Барсом» до 30 апреля 2025 года. 34-летний Войнов в нынешнем сезоне сыграл 45 матчей, включая плей-офф, где набрал 14 (1+13) очков с показателем полезности «+2». 37-летний Шипачёв в регулярке и Кубке Гагарина провёл 67 встреч, где записал на свой счёт 46 (14+32) результативных баллов.", "image": "uploads/2024/03/19/agent-shipachyova-i-vojnova-.jpg", "create_date": "2024-03-19T12:08:14.273Z", "update_date": "2024-03-19T12:44:41.927Z", "is_published": true, "category": 2}}, {"model": "sport_news.article", "pk": 6, "fields": {"title": "Кравец ответил на вопрос, что не получилось за время его пребывания в «Авангарде»", "content": "Бывший главный тренер «Авангарда» Михаил Кравец ответил на вопрос, что не получилось за время его пребывания в омском клубе.\r\n\r\n«Что не получилось за время моего пребывания в «Авангарде»? Да в принципе всё получилось. Все игроки, которые приходили, — все добавили, все играли. Кто бы ни играл, все выполняли свою работу. Может быть, все выполняли по-разному. Конечно, хотелось, чтобы мы более стабильно играли. Хотя достаточно того, что мы 43 матча выиграли и установил рекорд чемпионатов КХЛ», — сказал Кравец в беседе с корреспондентом «Чемпионата» Владимиром Лаевским.\r\n\r\nНакануне омский клуб проиграл «Локомотиву» в серии второго раунда Кубка Гагарина — 2024 со счётом 0:7. Исполняющим обязанности главного тренера «ястребов» назначен Сергей Звягин.", "image": "uploads/2024/03/19/kravec-otvetil-na-vopros-chto-ne-poluchilos-.jpg", "create_date": "2024-03-19T12:10:09.937Z", "update_date": "2024-03-19T12:44:05.781Z", "is_published": true, "category": 2}}, {"model": "sport_news.article", "pk": 7, "fields": {"title": "Матвей Сафонов покинул расположение сборной России", "content": "Вратарь сборной России Матвей Сафонов покинул расположение национальной команды, сообщает официальный сайт РФС. Голкипер вернётся в «Краснодар».\r\n\r\nВчера, 21 марта, Сафонов сыграл за сборную России в товарищеском матче с Сербией, оставив ворота россиян в неприкосновенности (4:0). Как сообщается на сайте РФС, решение отпустить вратаря со сбора было принято тренерским штабом национальной команды.\r\n\r\nОтметим, что в расположении сборной России после отъезда Сафонова осталось ещё три вратаря: Андрей Лунёв, Юрий Лодыгин и Александр Максименко. Российской национальной команде предстоит сыграть ещё один матч в марте. В ближайший понедельник, 25-го числа, сборная России в Москве примет Парагвай. Встреча пройдёт на стадионе «ВТБ Арена». Стартовый свисток прозвучит в 20:00 по московскому времени.", "image": "uploads/2024/03/22/matvej-safonov-pokinul-raspo.jpg", "create_date": "2024-03-22T10:27:18.736Z", "update_date": "2024-03-22T10:27:18.736Z", "is_published": true, "category": 1}}, {"model": "sport_news.article", "pk": 8, "fields": {"title": "Сафиуллин обыграл Шварцмана на старте турнира в Майами", "content": "Российский теннисист Роман Сафиуллин вышел во второй круг турнира в Майами. В матче первого круга он обыграл аргентинца Диего Шварцмана со счётом 6:2, 6:4.\r\nПродолжительность встречи составила 1 час 27 минут. За это время Сафиуллин сделал шесть подач навылет, допустил одну двойную ошибку и реализовал пять из семи брейк-пойнтов. На счету Шварцмана одна двойная ошибка и два реализованных брейк-пойнта из семи\r\n\r\nВо втором круге Сафиуллин встретится с итальянцем Лоренцо Музетти.\r\n\r\nТурнир в Майами проходит с 19 по 30 марта. Общий призовой фонд турнира составляет $ 8,9 млн. Действующим победителем турнира является россиянин Даниил Медведев, который в финальном матче прошлого года обыграл представителя Италии Янника Синнера.", "image": "uploads/2024/03/22/safiullin-obygral-shvarcmana-na-starte-turnira-v-majami_17110732851461140036.jpg", "create_date": "2024-03-22T10:28:18.986Z", "update_date": "2024-03-22T10:28:18.986Z", "is_published": true, "category": 3}}, {"model": "sport_news.article", "pk": 9, "fields": {"title": "Сборная Архангельской области одержала победу в мужской эстафете на чемпионате России", "content": "Сегодня, 22 марта, в Малиновке (Архангельская область) состоялась мужская эстафетная гонка в рамках Альфа-Банк чемпионата России — 2024. Лучшей в этой гонке стала команда Архангельской области, в составе которой выступили лыжники Александр Терентьев, Алексей Червоткин, Савелий Коростелёв и Александр Большунов.\r\n\r\nВторое место заняла команда Тюменской области, третьей стала сборная Республики Татарстан.\r\n\r\nЛыжные гонки. Чемпионат России — 2024, Малиновка.\r\nЭстафета, мужчины.\r\n\r\n1. Архангельская область (Александр Терентьев, Алексей Червоткин, Савелий Коростелёв, Александр Большунов) — 1:11.22,7.\r\n2. Тюменская область (Андрей Парфёнов, Евгений Белов, Денис Спицов, Иван Якимушкин) — отставание 13,3 секунды.\r\n3. Республика Татарстан — 1(Андрей Ларьков, Сергей Ардашев, Антон Тимашов, Иван Горбунов) +30,9.", "image": "uploads/2024/03/22/sbornaya-arhangelskoj-oblasti-oderzhala-pobedu-v-muzhskoj-estafete.jpg", "create_date": "2024-03-22T10:29:14.832Z", "update_date": "2024-03-22T10:29:14.832Z", "is_published": true, "category": 4}}, {"model": "sport_news.article", "pk": 10, "fields": {"title": "Кучеров занял 4-е место в НХЛ по скорости достижения 120 очков среди крайних форвардов", "content": "Закончился очередной матч регулярного чемпионата Национальной хоккейной лиги, в котором «Сан-Хосе Шаркс» принимал «Тампа-Бэй Лайтнинг». Встреча прошла в Сан-Хосе (США) на стадионе «Эс-Эй-Пи-центр» и завершилась победой гостей со счётом 4:1.\r\n\r\nРоссийский нападающий «Тампы» Никита Кучеров записал на свой счёт четыре результативные передачи. Таким образом, форвард набрал своё 122-е (41+81) очко за 68 матчей нынешнего сезона.\r\n\r\nКак сообщает аккаунт StatsCentre в социальной сети Х (ранее Twitter), Никита Кучеров занял четвёртое место в НХЛ по скорости достижения 120 очков среди крайних форвардов. Он сравнялся с Ги Лефлëром, которых также набирал 120+ очков за 68 встреч. На третьем месте — Яри Курри (66), на втором — Майк Босси (64). Рекорд принадлежит Яромиру Ягру (63).", "image": "uploads/2024/03/22/kucherov-zanyal-4-e-mesto-v-nhl-po-skorosti-dostizheniya.jpg", "create_date": "2024-03-22T10:30:14.666Z", "update_date": "2024-03-22T10:30:14.666Z", "is_published": true, "category": 2}}, {"model": "sport_news.article", "pk": 11, "fields": {"title": "Танасиевич: Бабич был в трансферных списках московского «Динамо»", "content": "Селекционер московского «Динамо» Йован Танасиевич рассказал, что бело-голубые интересовались центральным защитником сборной Сербии Срджаном Бабичем, который сейчас является игроком «Спартака».\r\n\r\n«Знаю, что Бабич был в наших списках. Там вообще много футболистов. Не знаю, в «Динамо», например, есть Роберто Фернандес — считаю, он сильнее Бабича», — приводит слова Танасиевича Sport24.\r\n\r\nСрджан Бабич является игроком красно-белых с августа 2023 года. В нынешнем сезоне сербский футболист принял участие в 14 матчах «Спартака» во всех турнирах, в которых отметился двумя голами. Действующее трудовое соглашение игрока с клубом рассчитано до лета 2026 года. Согласно информации, представленной на портале Transfermarkt, рыночная стоимость футболиста составляет € 4 млн.", "image": "uploads/2024/03/22/tanasievich-babich-byl-v-tra.jpg", "create_date": "2024-03-22T10:30:59.359Z", "update_date": "2024-03-22T10:30:59.359Z", "is_published": true, "category": 1}}, {"model": "sport_news.article", "pk": 12, "fields": {"title": "Илья Ишков: из «Урала» можно уехать в Европу, вспомните пример Зинченко и «Уфы»", "content": "18-летний полузащитник «Урала» и молодёжной сборной России Илья Ишков ответил на вопрос, видит ли себя в будущем в европейском чемпионате.\r\n\r\n«Не хочу загадывать. Безусловно, мне бы хотелось играть в Европе в хорошем клубе. Но для этого ещё предстоит много работы. Для начала стоит стать стопроцентным игроком стартового состава «Урала».\r\n\r\nМожно ли из «Урала» уехать в Европу? Почему нет? Можно вспомнить пример Зинченко, который из «Уфы» перешёл в «Манчестер Сити». Для всех это было неожиданно. Думаю, что из любого клуба можно уехать в Европу», — приводит слова Ишкова «Матч ТВ».\r\n\r\nНапомним, Зинченко играл за «Уфу» с 2015 по 2016 год, после чего перешёл в английский «Манчестер Сити». Летом 2022 года украинец перебрался в «Арсенал».\r\n\r\nВ нынешнем сезоне 18-летний Илья Ишков провёл за «Урал» 26 матчей во всех турнирах, где отметился одним забитым мячом и одной результативной передачей. Действующий контракт футболиста с клубом из Екатеринбурга рассчитан до 30 июня 2025 года. Интернет-портал Transfermarkt оценивает рыночную стоимость игрока в € 400 тыс.\r\n\r\nНапомним, после 20 туров Российской Премьер-Лиги нынешнего сезона «Урал» располагается на 13-м месте в турнирной таблице, набрав 19 очков. В следующем матче внутреннего первенства подопечные Виктора Гончаренко сыграют со «Спартаком» на выезде.", "image": "uploads/2024/03/22/ilya-ishkov-iz-urala-mozhno-.jpg", "create_date": "2024-03-22T10:33:39.718Z", "update_date": "2024-03-22T10:33:39.718Z", "is_published": true, "category": 1}}, {"model": "sport_news.article", "pk": 13, "fields": {"title": "«Ожидал, что будет хуже». Медведев — о чилийских болельщиках в матче с Харри", "content": "Четвёртая ракетка мира российский теннисист Даниил Медведев высказался о чилийских болельщиках, которые поддерживали его соперника, представителя Чили Николаса Харри, в матче 1/4 финала турнира серии «Мастерс» в Майами (США). Встреча завершилась со счётом 6:2, 7:6 (9:7) в пользу Медведева.\r\n\r\n«Честно говоря, я был к этому готов и ожидал, что будет хуже. Его поддерживали чилийские болельщики, но я должен сказать, что атмосфера была довольно приятной. Много раз судья обращался к нам и спрашивал: «Игроки готовы?» Но я отвечал: «Мне всё равно, на самом деле всё не так плохо. Бывало и хуже». Мне понравилась атмосфера в этом матче. Я чувствовал, что за меня тоже болеют люди, возможно, не чилийцы, но да, я хорошо чувствовал себя на корте», — сказал Медведев на пресс-конференции.", "image": "uploads/2024/03/28/ozhidal-chto-budet-huzhe-medvedev-o-chilijskih.jpg", "create_date": "2024-03-28T09:37:06.616Z", "update_date": "2024-03-28T09:37:06.616Z", "is_published": true, "category": 3}}, {"model": "sport_news.article", "pk": 14, "fields": {"title": "«Бавария» может назначить экс-тренера «Спартака» после ухода Тухеля", "content": "Мюнхенская «Бавария» рассматривает кандидатуру главного тренера «Астон Виллы» Унаи Эмери, который ранее был менеджером «Спартака», «ПСЖ» и «Вильярреала». Об этом сообщает TZ.\r\n\r\nПо информации источника, бывший игрок «Баварии» и нынешний тренер «Байера» Хаби Алонсо является главной целью мюнхенского клуба, однако из-за высокого интереса к испанскому менеджеру со стороны «Ливерпуля», который покинет Юрген Клопп по окончании сезона, немецкий клуб рассматривает и альтернативные варианты.\r\n\r\nРанее сообщалось, что спортивный директор «Баварии» Макс Эберль встречался с главным тренером английского «Брайтона» Роберто Де Дзерби. По итогам встречи итальянский специалист попросил время на принятие решения, так как в его услугах также заинтересован ряд больших клубов Европы.\r\n\r\n«Баварию» в данный момент возглавляет Томас Тухель, который покинет немецкий клуб по завершении сезона-2023/2024.", "image": "uploads/2024/03/28/bavariya-mozhet-naznachit-eks-trenera.jpg", "create_date": "2024-03-28T09:38:21.332Z", "update_date": "2024-03-28T09:38:21.332Z", "is_published": true, "category": 1}}, {"model": "sport_news.article", "pk": 18, "fields": {"title": "Виктория Сливко одержала победу в марафоне на ЧР в Увате", "content": "В рамках Альфа-Банк чемпионата России по биатлону — 2024 в Увате состоялся женский марафон на 30 км. Победу в гонке одержала Виктория Сливко. Стреляющая лыжница, представляющая сборную Тюменской области, допустила четыре промаха и преодолела дистанцию за 1:38.15,3.\r\n\r\nВторое место в марафоне досталось представительнице Свердловской области Ирине Казакевич. Она допустила шесть промахов и отстала от лидера на 26,9 секунды. Тройку призёров замкнула биатлонистка из Москвы Анастасия Гореева.\r\n\r\nБиатлон. Чемпионат России — 2024, Уват.\r\nМарафон, 30 км. Женщины\r\n\r\n1. Виктория Сливко (Тюменская область) — 1:38.15,3 (4).\r\n2. Ирина Казакевич (Свердловская область) — отставание 26,9 секунды (6).\r\n3. Анастасия Гореева (Москва) +2.14,3 (10).", "image": "", "create_date": "2024-04-05T09:39:38.258Z", "update_date": "2024-04-05T09:41:13.228Z", "is_published": true, "category": 4}}, {"model": "sport_news.article", "pk": 19, "fields": {"title": "Карим Халили выиграл марафон на 40 км на чемпионате России в Увате", "content": "В Увате на Альфа-Банк чемпионате России по биатлону сезона-2023/2024 состоялся мужской марафон на 40 км. Победу в этой гонке одержал российский биатлонист Карим Халили. Спортсмен, представляющий команду Москвы, допустил три промаха и преодолел дистанцию за 1:57.41,7.\r\n\r\nВторое место в этой гонке занял представитель команды ХМАО-Югры Никита Поршнев, допустивший семь промахов и отставший от лидера на 1.01,6. Тройку призёров замкнул биатлонист из Пермского края Иван Колотов.\r\n\r\nБиатлон. Чемпионат России — 2024, Уват.\r\nМарафон, 40 км. Мужчины\r\n\r\n1. Карим Халили (Москва) — 1:57.41,7 (3 промаха).\r\n2. Никита Поршнев (ХМАО-Югра) — отставание 1.01,6 секунды (7).\r\n3. Иван Колотов (Пермский край) +1.04,6 (5).\r\n\r\nЗавтра, 5 апреля, на чемпионате России по биатлону состоится женская гонка на 30 км.", "image": "", "create_date": "2024-04-05T09:48:08.277Z", "update_date": "2024-04-05T09:48:34.821Z", "is_published": true, "category": 4}}, {"model": "sport_news.article", "pk": 22, "fields": {"title": "Заварухин — после 2:3 от «Металлурга»: охота больше от нападающих", "content": "Главный тренер «Автомобилиста» Николай Заварухин прокомментировал поражение (2:3 ОТ) в третьем матче полуфинальной серии Кубка Гагарина с «Металлургом».\r\n«Быстрый матч с обеих сторон, были моменты в первом периоде и у соперника, и у нас. Во втором периоде «Металлург» был быстрее, делал наложения, не смогли долго выйти из зоны в паре моментов, это дало отпечаток. Здорово, что вытащили матч, но пропустили лёгкий на первый взгляд гол, который решил исход матча.\r\n\r\nСостояние Хрипунова после травмы? Не смогу сейчас ответить на этот вопрос.\r\n\r\nНеготовыми вышли на овертайм? Не скажу так, были неплохие моменты, у Мэйсека добивание. Были эмоции, хорошие эмоции в раздевалке после гола.\r\n\r\nБолее агрессивная игра в равных составах? Если честно, охота больше от нападающих, ждём большего, в следующих матчах будет больше угрозы у ворот «Металлурга», надеюсь», — передаёт слова Заварухина корреспондент «Чемпионата» Родион Власов.\r\n\r\n«Автомобилист» уступает в серии — 1-2. Следующая игра состоится на домашнем льду екатеринбуржцев 9 апреля.", "image": "uploads/2024/04/07/zavaruhin-posle-2-3-ot-metallurga-ohota-bolshe-.jpg", "create_date": "2024-04-07T15:57:35.265Z", "update_date": "2024-04-07T15:58:20.231Z", "is_published": true, "category": 2}}, {"model": "sport_news.article", "pk": 39, "fields": {"title": "Йоханнес Клебо объявил о возвращении в сборную Норвегии", "content": "Пятикратный олимпийский чемпион, девятикратный чемпион мира норвежский лыжник Йоханнес Клебо объявил о возвращении в сборную Норвегии. Спортсмен проведёт в расположении национальной команды следующие два сезона.\r\n\r\n«Мне нравится быть с товарищами по команде, я хорошо со всеми общаюсь, с персоналом тоже нет проблем. В прошлом году обстоятельства сложились так, что находиться в команде оказалось сложно. Но мы добились прогресса. Я рад, что мы достигли соглашения и заключили его заблаговременно. Официально я присоединюсь к сборной 1 мая», — приводит слова Клебо Dagbladet.\r\n\r\nНапомним, в прошлом году Клебо покинул национальную команду из-за разногласий с Норвежской лыжной ассоциацией в вопросах условий подготовки и взаимодействия со спонсорами. Перед стартом сезона Клебо подписал стандартный контракт с организацией, позволяющий выступать на гонках Кубка мира.", "image": "uploads/2024/04/12/johannes-klebo-obyavil-o-vozvraschenii-v-sbornuyu-norvegii_1712927071_Kd4JNoh.jpg", "create_date": "2024-04-12T15:17:08.011Z", "update_date": "2024-04-12T15:17:08.097Z", "is_published": true, "category": 4}}, {"model": "sport_news.article", "pk": 40, "fields": {"title": "Погребняк: уход Абаскаля? Не понимаю политику «Спартака», но хуже точно не будет", "content": "Бывший нападающий «Спартака» Павел Погребняк высказался относительно ситуации с главным тренером красно-белых Гильермо Абаскалем, который может быть уволен в скором времени.\r\n\r\n«Не знаю, что происходит в «Спартаке», потому что надо быть внутри клуба и внутри этой ситуации. Кто может заменить Гильермо Абаскаля в случае ухода? Не понимаю политики клуба, но хуже уже точно не будет. Возможно, «Спартак» выиграет все оставшиеся матчи, и мы даже не будем обсуждать этот вопрос», – приводит слова Погребняка Metaratings.\r\n\r\nНапомним, Абаскаль был назначен на пост главного тренера «Спартака» в июле 2022 года. Под его руководством красно-белые провели 73 матча во всех турнирах, в которых 36 раз выиграли, 15 раз сыграли вничью и 22 раза проиграли.\r\n\r\nПосле 22 матчей чемпионата России нынешнего сезона московский клуб набрал 35 очков и занимает шестое место. В следующем туре «Спартак» сыграет с «Сочи». Матч состоится 13 апреля.", "image": "uploads/2024/04/12/pogrebnyak-uhod-abaskalya-ne.jpg", "create_date": "2024-04-12T15:22:46.405Z", "update_date": "2024-04-12T15:22:46.489Z", "is_published": true, "category": 1}}, {"model": "sport_news.article", "pk": 46, "fields": {"title": "Алексей Морозов рассказал о плюсах увеличения числа легионеров в КХЛ", "content": "Президент КХЛ Алексей Морозов заявил, что изменение лимита на легионеров с трёх до пяти должно позитивно сказаться на развитии молодых игроков, так как это поможет получать необходимую практику во время отстранения сборной России.\r\n\r\n«Очень жалко ребят 16-20 лет, которые не могут получить полноценный международный опыт, выступая за сборную. Они по-другому развиваются. Что будет с ними, когда они окажутся на международных соревнованиях, трудно сказать. Но здесь и сейчас нам нужна сильная, конкурентная лига с равными командами, в которой молодые игроки смогут получать достойный опыт. И тогда, вернувшись на международную арену, мы будем на уровне», — приводит слова Морозова «Российская газета».\r\n\r\nНапомним, в начале апреля появилась информация, что в следующем сезоне КХЛ планирует вернуться к лимиту в пять легионеров. Текущий сезон стал первым, в котором лимит на иностранных хоккеистов был установлен в количестве трёх человек.", "image": "uploads/2024/04/12/aleksej-morozov-rasskazal-o-_jJkk8EM.jpg", "create_date": "2024-04-12T17:32:20.137Z", "update_date": "2024-04-12T17:32:20.137Z", "is_published": true, "category": 2}}, {"model": "sport_news.article", "pk": 47, "fields": {"title": "Синнер обыграл Руне и вышел в полуфинал «Мастерса» в Монте-Карло", "content": "В матче 1/4 финала грунтового турнира серии «Мастерс» в Монте-Карло (Монако) вторая ракетка мира итальянский теннисист Янник Синнер одержал победу над представителем Дании Хольгером Руне (седьмой в рейтинге ATP). Встреча завершилась со счётом 6:4, 6:7 (6:8), 6:3 в пользу итальянского спортсмена.\r\nПродолжительность матча составила 2 часа 42 минуты. Синнер в этой встрече пять раз подал навылет, допустил две двойные ошибки и реализовал два брейк-пойнта из восьми. На счету Руне шесть эйсов и шесть двойных ошибок.\r\nВ полуфинале «Мастерса» в Монте-Карло Янник Синнер сыграет с 12-й ракеткой мира греческим теннисистом Стефаносом Циципасом, который ранее победил россиянина Карена Хачанова. Турнир завершится 14 апреля.", "image": "uploads/2024/04/12/sinner-obygral-rune-i-vyshel-.jpg", "create_date": "2024-04-12T17:47:48.720Z", "update_date": "2024-04-12T17:47:48.720Z", "is_published": true, "category": 3}}, {"model": "sport_news.article", "pk": 48, "fields": {"title": "«Я тоже человек!» Руне обвинил судью в предвзятости по ходу матча с Синнером в Монте-Карло", "content": "Седьмая ракетка мира, 20-летний датский теннисист Хольгер Руне обвинил судью его матча с итальянцем Янником Синнером в четвертьфинале грунтового турнира серии «Мастерс» в Монте-Карло (Монако) в предвзятости.\r\n\r\nРуне озвучил это после ошибки судьи. Инцидент произошёл на тай-брейке второго сета, при счёте 3:2 в пользу Хольгера. Судья не позволил датчанину сделать мини-брейк: изначально он зафиксировал аут после удара Синнера, однако, спустившись с вышки, изменил своё решение. При этом система Hawk-Eye тоже показала, что мяч Синнера попал в аут.\r\nРуне: ты все решения принимаешь против меня.\r\nСудья: я ничего не имею против тебя.\r\nРуне: я тоже человек! Так что, пожалуйста, уважай меня.\r\n\r\nОтметим, что данный инцидент всё же не помешал Руне выиграть тай-брейк (8:6), однако третий, решающий сет матча остался за Синнером.", "image": "uploads/2024/04/12/ya-tozhe-chelovek-rune-obvinil-sudyu-v-predvzyatosti-po-hodu-matcha-s-.jpg", "create_date": "2024-04-12T17:52:23.325Z", "update_date": "2024-04-15T19:22:40.398Z", "is_published": true, "category": 3}}, {"model": "sport_news.article", "pk": 49, "fields": {"title": "Дмитрий Бивол и Артур Бетербиев впервые встретились перед боем", "content": "Чемпионы мира в полутяжёлом весе (до 79,4 кг) россияне Дмитрий Бивол (22-0, 11 KO) и Артур Бетербиев (20-0, 20 KO) впервые встретились перед своим поединком на вступительной пресс-конференции, состоявшейся сегодня, 15 апреля, в Лондоне (Великобритания).\r\nДмитрию Биволу 33 года. В своём последнем бою, состоявшемся в декабре, россиянин победил единогласным судейским решением британца Линдона Артура, проведя 11-ю защиту титула WBA.\r\n\r\nАртуру Бетербиеву 38 лет. В своём последнем бою в январе уроженец Хасавюрта досрочно остановил в седьмом раунде победителя Всемирной боксёрской суперсерии (WBSS) и экс-чемпиона во втором среднем весе (до 76,2 кг) британца Каллума Смита, отстояв титулы WBC, IBF и WBO.", "image": "uploads/2024/04/15/1713203036674356569.jpg", "create_date": "2024-04-15T18:57:58.198Z", "update_date": "2024-04-15T18:57:58.198Z", "is_published": true, "category": 4}}, {"model": "sport_news.article", "pk": 50, "fields": {"title": "Источник: капитан московского «Динамо» Андрей Миронов перейдёт в «Спартак»", "content": "Капитан московского «Динамо» Андрей Миронов перейдёт в «Спартак», сообщает «Спорт-экспресс». По информации источника, защитник бело-голубых не договорился с руководством «Динамо» по финансовым условиям, тогда как «Спартак» предложил ему куда более выгодный контракт в плане бонусной части соглашения.\r\n\r\n29-летний Миронов установил рекорд «Динамо» по количеству игр в чемпионатах страны. Всего в 644 матчах Миронов набрал 173 очка — забросил 43 шайбы и отдал 130 результативных передач с показателем полезности «+48».\r\n\r\nВ прошедшем регулярном чемпионате КХЛ «Динамо» заняло первое место. В плей-офф бело-голубые во втором раунде уступили «Трактору» в четырёх матчах. «Спартак» также дошёл до второго раунда Кубка Гагарина, где в шести матчах уступил «Металлургу».", "image": "uploads/2024/04/16/istochnik-kapitan-moskovskog.jpg", "create_date": "2024-04-16T18:22:02.393Z", "update_date": "2024-04-16T18:22:02.393Z", "is_published": true, "category": 2}}, {"model": "sport_news.category", "pk": 1, "fields": {"title": "Футбол"}}, {"model": "sport_news.category", "pk": 2, "fields": {"title": "Хоккей"}}, {"model": "sport_news.category", "pk": 3, "fields": {"title": "Теннис"}}, {"model": "sport_news.category", "pk": 4, "fields": {"title": "Другое"}}]